{
  "bundler": "webpack",
  "shimport": null,
  "assets": {
    "vendors~billing$45address~cart~category~change$45password~checkout~checkout_invoice_$id~compare_$id~~c2602e8a": "dfbcc80908925291cc1f/vendors~billing$45address~cart~category~change$45password~checkout~checkout_invoice_$id~compare_$id~~c2602e8a.0.js",
    "vendors~billing$45address~cart~category~change$45password~checkout~checkout_invoice_$id~compare_$id~~5b6c1837": "dfbcc80908925291cc1f/vendors~billing$45address~cart~category~change$45password~checkout~checkout_invoice_$id~compare_$id~~5b6c1837.1.js",
    "vendors~billing$45address~cart~category~change$45password~checkout~checkout_invoice_$id~compare_$id~~bf52b456": "dfbcc80908925291cc1f/vendors~billing$45address~cart~category~change$45password~checkout~checkout_invoice_$id~compare_$id~~bf52b456.2.js",
    "vendors~billing$45address~cart~category~change$45password~checkout~checkout_invoice_$id~compare_$id~~06857c4e": [
      "vendors~billing$45address~cart~category~change$45password~checkout~checkout_invoice_$id~compare_$id~~06857c4e.css",
      "dfbcc80908925291cc1f/vendors~billing$45address~cart~category~change$45password~checkout~checkout_invoice_$id~compare_$id~~06857c4e.3.js"
    ],
    "about": "dfbcc80908925291cc1f/about.6.js",
    "billing$45address": "dfbcc80908925291cc1f/billing$45address.7.js",
    "cart": "dfbcc80908925291cc1f/cart.8.js",
    "category": "dfbcc80908925291cc1f/category.9.js",
    "change$45password": "dfbcc80908925291cc1f/change$45password.10.js",
    "checkout": "dfbcc80908925291cc1f/checkout.11.js",
    "checkout_invoice_$id": "dfbcc80908925291cc1f/checkout_invoice_$id.12.js",
    "compare_$id": "dfbcc80908925291cc1f/compare_$id.13.js",
    "credit$45card": "dfbcc80908925291cc1f/credit$45card.14.js",
    "device_$id": [
      "device_$id.css",
      "dfbcc80908925291cc1f/device_$id.15.js"
    ],
    "empty": "dfbcc80908925291cc1f/empty.16.js",
    "faq": "dfbcc80908925291cc1f/faq.17.js",
    "favorites": "dfbcc80908925291cc1f/favorites.18.js",
    "forgot$45password": "dfbcc80908925291cc1f/forgot$45password.19.js",
    "index": [
      "index.css",
      "dfbcc80908925291cc1f/index.20.js"
    ],
    "main": "dfbcc80908925291cc1f/main.js",
    "my$45account": [
      "my$45account.css",
      "dfbcc80908925291cc1f/my$45account.22.js"
    ],
    "my$45devices": [
      "my$45devices.css",
      "dfbcc80908925291cc1f/my$45devices.23.js"
    ],
    "my$45devices_$id": [
      "my$45devices_$id.css",
      "dfbcc80908925291cc1f/my$45devices_$id.24.js"
    ],
    "my$45devices_add$45device": "dfbcc80908925291cc1f/my$45devices_add$45device.25.js",
    "my$45devices_edit$45device_$id": "dfbcc80908925291cc1f/my$45devices_edit$45device_$id.26.js",
    "my$45devices_offers_$id": "dfbcc80908925291cc1f/my$45devices_offers_$id.27.js",
    "my$45devices_post$45device_$id": [
      "my$45devices_post$45device_$id.css",
      "dfbcc80908925291cc1f/my$45devices_post$45device_$id.28.js"
    ],
    "my$45devices_post$45device_edit_$id": [
      "my$45devices_post$45device_edit_$id.css",
      "dfbcc80908925291cc1f/my$45devices_post$45device_edit_$id.29.js"
    ],
    "my$45notification": "dfbcc80908925291cc1f/my$45notification.30.js",
    "my$45offers_$id": [
      "my$45offers_$id.css",
      "dfbcc80908925291cc1f/my$45offers_$id.31.js"
    ],
    "my$45profile": [
      "my$45profile.css",
      "dfbcc80908925291cc1f/my$45profile.32.js"
    ],
    "my$45purchases": "dfbcc80908925291cc1f/my$45purchases.33.js",
    "my$45purchases_$id": "dfbcc80908925291cc1f/my$45purchases_$id.34.js",
    "my$45sales": "dfbcc80908925291cc1f/my$45sales.35.js",
    "my$45sales_$id": "dfbcc80908925291cc1f/my$45sales_$id.36.js",
    "my$45sales_checkout_$id": "dfbcc80908925291cc1f/my$45sales_checkout_$id.37.js",
    "my$45transactions": "dfbcc80908925291cc1f/my$45transactions.38.js",
    "my$45transactions_$id": "dfbcc80908925291cc1f/my$45transactions_$id.39.js",
    "my$45transactions_dispute_$id": "dfbcc80908925291cc1f/my$45transactions_dispute_$id.40.js",
    "my$45transactions_pickup_$id": "dfbcc80908925291cc1f/my$45transactions_pickup_$id.41.js",
    "my$45transactions_pickup_purchase_$id": "dfbcc80908925291cc1f/my$45transactions_pickup_purchase_$id.42.js",
    "my$45transactions_submit$45passcode_$id": "dfbcc80908925291cc1f/my$45transactions_submit$45passcode_$id.43.js",
    "my$45transactions_transaction$45confirm$45scan_$id": "dfbcc80908925291cc1f/my$45transactions_transaction$45confirm$45scan_$id.44.js",
    "my$45transactions_transaction$45scan_$id": "dfbcc80908925291cc1f/my$45transactions_transaction$45scan_$id.45.js",
    "my$45wallet": "dfbcc80908925291cc1f/my$45wallet.46.js",
    "my$45wishlists": "dfbcc80908925291cc1f/my$45wishlists.47.js",
    "notfound": "dfbcc80908925291cc1f/notfound.48.js",
    "notification": "dfbcc80908925291cc1f/notification.49.js",
    "open$45dispute": "dfbcc80908925291cc1f/open$45dispute.50.js",
    "privacy": "dfbcc80908925291cc1f/privacy.51.js",
    "reset$45password": "dfbcc80908925291cc1f/reset$45password.52.js",
    "shipping$45and$45billing": "dfbcc80908925291cc1f/shipping$45and$45billing.53.js",
    "sign$45in": "dfbcc80908925291cc1f/sign$45in.54.js",
    "sign$45up": "dfbcc80908925291cc1f/sign$45up.55.js",
    "test": "dfbcc80908925291cc1f/test.56.js",
    "test_PcCheckboxAll": "dfbcc80908925291cc1f/test_PcCheckboxAll.57.js",
    "test_com": "dfbcc80908925291cc1f/test_com.58.js",
    "vendors~test": "dfbcc80908925291cc1f/vendors~test.59.js",
    "vendors~test_com": [
      "vendors~test_com.css",
      "dfbcc80908925291cc1f/vendors~test_com.60.js"
    ]
  },
  "css": {
    "main": null
  }
}